flask_zookeeper.py
flask_zookeeper-0.0.4.dist-info/zip-safe
flask_zookeeper-0.0.4.dist-info/top_level.txt
flask_zookeeper-0.0.4.dist-info/METADATA
flask_zookeeper-0.0.4.dist-info/DESCRIPTION.rst
flask_zookeeper-0.0.4.dist-info/metadata.json
flask_zookeeper-0.0.4.dist-info/WHEEL
flask_zookeeper-0.0.4.dist-info/RECORD
