Metadata-Version: 2.0
Name: flask-zookeeper
Version: 0.0.4
Summary: Flask Zookeeper client
Home-page: https://github.com/cdumay/flask-zookeeper
Author: Cedric DUMAY
Author-email: cedric.dumay@gmail.com
License: Apache License
Platform: UNKNOWN
Classifier: Programming Language :: Python
Requires-Dist: flask
Requires-Dist: kazoo
